Metadata-Version: 2.1
Name: startmlproject
Version: 1.0.0
Summary: A custom Machine Learning project creation tool.
Home-page: https://github.com/MadhuSuniL/startmlproject
Author: Madhu Sunil
Classifier: Programming Language :: Python :: 3
Classifier: License :: OSI Approved :: MIT License
Classifier: Operating System :: OS Independent
Requires-Python: >=3.6
